boa/__init__.py
boa_str-1.1.0.dist-info/DESCRIPTION.rst
boa_str-1.1.0.dist-info/METADATA
boa_str-1.1.0.dist-info/RECORD
boa_str-1.1.0.dist-info/WHEEL
boa_str-1.1.0.dist-info/metadata.json
boa_str-1.1.0.dist-info/top_level.txt
