Metadata-Version: 2.0
Name: boa-str
Version: 1.1.0
Summary: Convert strings to snakecase
Home-page: https://github.com/astronomerio/boa
Author: Astronomer
Author-email: taylor@astronomer.io
License: MIT License
Keywords: boa snakecase snake_case snake case inflector astronomer astronomerio
Platform: UNKNOWN
Classifier: Development Status :: 4 - Beta
Classifier: Intended Audience :: Developers
Classifier: License :: OSI Approved :: MIT License
Classifier: Programming Language :: Python :: 2.7
Classifier: Programming Language :: Python :: 3
Classifier: Programming Language :: Python :: 3.3
Classifier: Programming Language :: Python :: 3.4
Classifier: Programming Language :: Python :: 3.5
Classifier: Programming Language :: Python :: 3.6
Provides-Extra: dev
Requires-Dist: codecov; extra == 'dev'
Requires-Dist: cov-core; extra == 'dev'
Requires-Dist: nose2; extra == 'dev'
Requires-Dist: flake8; extra == 'dev'
Requires-Dist: invoke; extra == 'dev'
Requires-Dist: pycodestyle; extra == 'dev'
Requires-Dist: twine; extra == 'dev'
Provides-Extra: test
Requires-Dist: codecov; extra == 'test'
Requires-Dist: cov-core; extra == 'test'
Requires-Dist: nose2; extra == 'test'
